.DS_Store
streamlit_cookie/__init__.py
streamlit_cookie/cookie_manager.py
streamlit_cookie/encrypted_cookies.py
streamlit_cookie/build/asset-manifest.json
streamlit_cookie/build/index.html
streamlit_cookie/build/static/js/2.37a412b8.chunk.js
streamlit_cookie/build/static/js/2.37a412b8.chunk.js.LICENSE.txt
streamlit_cookie/build/static/js/2.37a412b8.chunk.js.map
streamlit_cookie/build/static/js/main.1d425697.chunk.js
streamlit_cookie/build/static/js/main.1d425697.chunk.js.map
streamlit_cookie/build/static/js/runtime-main.c713e1ba.js
streamlit_cookie/build/static/js/runtime-main.c713e1ba.js.map
streamlit_cookie-0.1.0.dist-info/METADATA
streamlit_cookie-0.1.0.dist-info/WHEEL
streamlit_cookie-0.1.0.dist-info/top_level.txt
streamlit_cookie-0.1.0.dist-info/RECORD
