Metadata-Version: 2.1
Name: streamlit-cookie
Version: 0.1.0
Summary: Access and save cookies from Streamlit
Author: jameisun
Author-email: jamiesun.net@gmail.com
Requires-Dist: cryptography
Requires-Dist: streamlit >=1.30.0
Provides-Extra: dev
Requires-Dist: pytest <7.0,>=6.2.2 ; extra == 'dev'
